zeent_api_client/__init__.py
zeent_api_client/apiclient.py
zeent_api_client-0.0.1.dist-info/METADATA
zeent_api_client-0.0.1.dist-info/WHEEL
zeent_api_client-0.0.1.dist-info/top_level.txt
zeent_api_client-0.0.1.dist-info/RECORD
